<?xml version="1.0" encoding="UTF-8"?>
<con:resource name="comments" path="/services/mobile/comments" id="0ac54969-5909-4a3b-8c53-49e286faaf88" xmlns:xsi="http://www.w3.org/2001/XMLSchema-instance" xmlns:con="http://eviware.com/soapui/config"><con:settings><con:setting id="0ac54969-5909-4a3b-8c53-49e286faaf88fileName">comments</con:setting></con:settings><con:parameters/><con:resource name="addcomments" path="addcomment/{sid}/{docid}" id="aa4913ca-c81d-4d1a-8b7a-ce1b5e72fdd7"><con:settings/><con:parameters><con:parameter required="true"><con:name>sid</con:name><con:value>sid</con:value><con:style>TEMPLATE</con:style><con:default>sid</con:default></con:parameter><con:parameter required="true"><con:name>docid</con:name><con:value>docid</con:value><con:style>TEMPLATE</con:style><con:default>docid</con:default></con:parameter></con:parameters><con:method name="Method 1" id="d38538e8-79f9-4ef5-9b63-639d1bb8ca52" method="POST"><con:settings/><con:parameters/><con:request name="Request 1" id="c737bd12-34b9-4eb2-a83a-64e7aa12b0d5" mediaType="application/json" postQueryString="false"><con:settings/><con:endpoint>http://localhost:8094/logicaldoc</con:endpoint><con:request/><con:credentials><con:selectedAuthProfile>Inherit From Parent</con:selectedAuthProfile><con:authType>No Authorization</con:authType></con:credentials><con:jmsConfig JMSDeliveryMode="PERSISTENT"/><con:parameters/></con:request></con:method></con:resource><con:resource name="addcommentform" path="addcommentform/{sid}/{docid}" id="595e9b2c-4a7f-49cd-9c97-27149416c2f2"><con:settings/><con:parameters><con:parameter required="true"><con:name>sid</con:name><con:value>sid</con:value><con:style>TEMPLATE</con:style><con:default>sid</con:default></con:parameter><con:parameter required="true"><con:name>docid</con:name><con:value>docid</con:value><con:style>TEMPLATE</con:style><con:default>docid</con:default></con:parameter></con:parameters><con:method name="Method 1" id="c8825f25-c2de-4594-8a75-bac7ab8634dd" method="POST"><con:settings/><con:parameters/><con:request name="Request 1" id="e39f4c92-950f-41e7-b660-9ee212014385" mediaType="application/json" postQueryString="false"><con:settings/><con:endpoint>http://localhost:8094/logicaldoc</con:endpoint><con:request/><con:credentials><con:selectedAuthProfile>Inherit From Parent</con:selectedAuthProfile><con:authType>No Authorization</con:authType></con:credentials><con:jmsConfig JMSDeliveryMode="PERSISTENT"/><con:parameters/></con:request></con:method></con:resource><con:resource name="getcomment" path="getcomments/{sid}/{docid}" id="7aa651a1-299e-44d4-9a05-57d62bbf4466"><con:settings/><con:parameters><con:parameter required="true"><con:name>sid</con:name><con:value>sid</con:value><con:style>TEMPLATE</con:style><con:default>sid</con:default></con:parameter><con:parameter required="true"><con:name>docid</con:name><con:value>docid</con:value><con:style>TEMPLATE</con:style><con:default>docid</con:default></con:parameter></con:parameters><con:method name="Method 1" id="4d1356a2-78c2-4797-8a8e-6647e0ad36f8" method="GET"><con:settings/><con:parameters/><con:request name="Request 1" id="66f74af3-0c55-4397-a5f4-2c89f1baf24b" mediaType="application/json"><con:settings/><con:endpoint>http://localhost:8094/logicaldoc</con:endpoint><con:request/><con:credentials><con:selectedAuthProfile>Inherit From Parent</con:selectedAuthProfile><con:authType>No Authorization</con:authType></con:credentials><con:jmsConfig JMSDeliveryMode="PERSISTENT"/><con:parameters/></con:request></con:method></con:resource></con:resource>